{
  "version": "4.5.7",
  "imageData": null,
  "fillColor": [
    255,
    0,
    0,
    128
  ],
  "lineColor": [
    0,
    255,
    0,
    128
  ],
  "imagePath": "dataset133.jpg",
  "imageHeight": 2160,
  "imageWidth": 3840,
  "shapes": [
    {
      "line_color": null,
      "fill_color": null,
      "shape_type": "polygon",
      "label": "Barrier",
      "group_id": 0,
      "points": [
        [
          0,
          1654
        ],
        [
          0,
          1360
        ],
        [
          213,
          1351
        ],
        [
          616,
          1327
        ],
        [
          1363,
          1279
        ],
        [
          1480,
          1268
        ],
        [
          1669,
          1256
        ],
        [
          1665,
          1266
        ],
        [
          1664,
          1290
        ],
        [
          1442,
          1345
        ],
        [
          1149,
          1410
        ],
        [
          1145,
          1410
        ],
        [
          1144,
          1403
        ],
        [
          1053,
          1424
        ],
        [
          1053,
          1431
        ],
        [
          1049,
          1432
        ],
        [
          358,
          1576
        ],
        [
          0,
          1654
        ]
      ]
    }
  ]
}