{
  "version": "4.5.7",
  "imageData": null,
  "fillColor": [
    255,
    0,
    0,
    128
  ],
  "lineColor": [
    0,
    255,
    0,
    128
  ],
  "imagePath": "dataset250.jpg",
  "imageHeight": 3024,
  "imageWidth": 4032,
  "shapes": [
    {
      "line_color": null,
      "fill_color": null,
      "shape_type": "polygon",
      "label": "Fence",
      "group_id": 0,
      "points": [
        [
          113,
          1237
        ],
        [
          54,
          1227
        ],
        [
          61,
          1192
        ],
        [
          12,
          1183
        ],
        [
          6,
          1214
        ],
        [
          5,
          1216
        ],
        [
          0,
          1214
        ],
        [
          0,
          1101
        ],
        [
          176,
          1131
        ],
        [
          163,
          1206
        ],
        [
          121,
          1199
        ],
        [
          113,
          1237
        ]
      ]
    },
    {
      "line_color": null,
      "fill_color": null,
      "shape_type": "polygon",
      "label": "Fence",
      "group_id": 0,
      "points": [
        [
          1773,
          1492
        ],
        [
          1759,
          1492
        ],
        [
          1764,
          1454
        ],
        [
          1691,
          1443
        ],
        [
          1685,
          1476
        ],
        [
          1646,
          1473
        ],
        [
          1651,
          1436
        ],
        [
          1595,
          1425
        ],
        [
          1587,
          1460
        ],
        [
          1549,
          1456
        ],
        [
          1554,
          1423
        ],
        [
          1532,
          1414
        ],
        [
          1499,
          1409
        ],
        [
          1491,
          1442
        ],
        [
          1488,
          1444
        ],
        [
          1459,
          1437
        ],
        [
          1464,
          1404
        ],
        [
          1413,
          1394
        ],
        [
          1404,
          1428
        ],
        [
          1376,
          1426
        ],
        [
          1381,
          1391
        ],
        [
          1337,
          1385
        ],
        [
          1331,
          1416
        ],
        [
          1301,
          1412
        ],
        [
          1294,
          1411
        ],
        [
          1299,
          1377
        ],
        [
          1253,
          1369
        ],
        [
          1246,
          1401
        ],
        [
          1229,
          1399
        ],
        [
          1216,
          1397
        ],
        [
          1221,
          1365
        ],
        [
          1178,
          1358
        ],
        [
          1173,
          1387
        ],
        [
          1169,
          1390
        ],
        [
          1146,
          1386
        ],
        [
          1153,
          1356
        ],
        [
          1108,
          1347
        ],
        [
          1102,
          1377
        ],
        [
          1097,
          1379
        ],
        [
          1059,
          1372
        ],
        [
          1062,
          1343
        ],
        [
          1044,
          1339
        ],
        [
          1013,
          1334
        ],
        [
          1006,
          1363
        ],
        [
          970,
          1358
        ],
        [
          975,
          1326
        ],
        [
          928,
          1320
        ],
        [
          922,
          1348
        ],
        [
          916,
          1350
        ],
        [
          883,
          1345
        ],
        [
          886,
          1313
        ],
        [
          829,
          1305
        ],
        [
          823,
          1336
        ],
        [
          818,
          1336
        ],
        [
          782,
          1331
        ],
        [
          787,
          1300
        ],
        [
          737,
          1293
        ],
        [
          729,
          1322
        ],
        [
          689,
          1319
        ],
        [
          692,
          1288
        ],
        [
          640,
          1280
        ],
        [
          634,
          1310
        ],
        [
          591,
          1306
        ],
        [
          592,
          1274
        ],
        [
          532,
          1264
        ],
        [
          530,
          1298
        ],
        [
          525,
          1298
        ],
        [
          480,
          1291
        ],
        [
          484,
          1257
        ],
        [
          436,
          1249
        ],
        [
          429,
          1279
        ],
        [
          381,
          1272
        ],
        [
          386,
          1242
        ],
        [
          327,
          1235
        ],
        [
          321,
          1267
        ],
        [
          276,
          1259
        ],
        [
          281,
          1225
        ],
        [
          224,
          1214
        ],
        [
          214,
          1251
        ],
        [
          177,
          1246
        ],
        [
          173,
          1245
        ],
        [
          173,
          1240
        ],
        [
          191,
          1134
        ],
        [
          707,
          1209
        ],
        [
          1165,
          1268
        ],
        [
          1832,
          1364
        ],
        [
          1833,
          1372
        ],
        [
          1822,
          1462
        ],
        [
          1817,
          1463
        ],
        [
          1778,
          1456
        ],
        [
          1773,
          1492
        ]
      ]
    },
    {
      "line_color": null,
      "fill_color": null,
      "shape_type": "polygon",
      "label": "Fence",
      "group_id": 0,
      "points": [
        [
          2041,
          1789
        ],
        [
          2015,
          1773
        ],
        [
          1973,
          1735
        ],
        [
          1948,
          1690
        ],
        [
          1945,
          1652
        ],
        [
          1932,
          1622
        ],
        [
          1879,
          1555
        ],
        [
          1851,
          1542
        ],
        [
          1860,
          1470
        ],
        [
          1845,
          1467
        ],
        [
          1858,
          1368
        ],
        [
          1867,
          1369
        ],
        [
          1879,
          1380
        ],
        [
          1879,
          1398
        ],
        [
          1930,
          1428
        ],
        [
          2041,
          1522
        ],
        [
          2094,
          1583
        ],
        [
          2041,
          1789
        ]
      ]
    },
    {
      "line_color": null,
      "fill_color": null,
      "shape_type": "polygon",
      "label": "Fence",
      "group_id": 0,
      "points": [
        [
          2124,
          1874
        ],
        [
          2114,
          1866
        ],
        [
          2104,
          1834
        ],
        [
          2095,
          1822
        ],
        [
          2084,
          1818
        ],
        [
          2082,
          1813
        ],
        [
          2129,
          1627
        ],
        [
          2133,
          1636
        ],
        [
          2134,
          1649
        ],
        [
          2140,
          1814
        ],
        [
          2124,
          1874
        ]
      ]
    },
    {
      "line_color": null,
      "fill_color": null,
      "shape_type": "polygon",
      "label": "Wall",
      "group_id": 1,
      "points": [
        [
          143,
          1312
        ],
        [
          1,
          1291
        ],
        [
          0,
          1215
        ],
        [
          5,
          1216
        ],
        [
          6,
          1214
        ],
        [
          11,
          1184
        ],
        [
          61,
          1193
        ],
        [
          54,
          1227
        ],
        [
          109,
          1237
        ],
        [
          114,
          1235
        ],
        [
          121,
          1199
        ],
        [
          163,
          1206
        ],
        [
          143,
          1312
        ]
      ]
    },
    {
      "line_color": null,
      "fill_color": null,
      "shape_type": "polygon",
      "label": "Wall",
      "group_id": 1,
      "points": [
        [
          1658,
          1552
        ],
        [
          1459,
          1529
        ],
        [
          1166,
          1469
        ],
        [
          778,
          1415
        ],
        [
          408,
          1352
        ],
        [
          166,
          1316
        ],
        [
          161,
          1315
        ],
        [
          161,
          1311
        ],
        [
          172,
          1246
        ],
        [
          214,
          1251
        ],
        [
          224,
          1214
        ],
        [
          281,
          1225
        ],
        [
          275,
          1259
        ],
        [
          318,
          1267
        ],
        [
          322,
          1264
        ],
        [
          327,
          1235
        ],
        [
          386,
          1242
        ],
        [
          381,
          1272
        ],
        [
          425,
          1279
        ],
        [
          430,
          1277
        ],
        [
          436,
          1249
        ],
        [
          484,
          1257
        ],
        [
          479,
          1291
        ],
        [
          525,
          1298
        ],
        [
          530,
          1298
        ],
        [
          532,
          1264
        ],
        [
          592,
          1274
        ],
        [
          591,
          1306
        ],
        [
          634,
          1310
        ],
        [
          640,
          1280
        ],
        [
          692,
          1288
        ],
        [
          689,
          1319
        ],
        [
          729,
          1322
        ],
        [
          737,
          1293
        ],
        [
          787,
          1300
        ],
        [
          782,
          1331
        ],
        [
          818,
          1336
        ],
        [
          823,
          1336
        ],
        [
          829,
          1305
        ],
        [
          886,
          1313
        ],
        [
          884,
          1345
        ],
        [
          921,
          1350
        ],
        [
          928,
          1320
        ],
        [
          975,
          1326
        ],
        [
          970,
          1358
        ],
        [
          1006,
          1363
        ],
        [
          1013,
          1334
        ],
        [
          1062,
          1342
        ],
        [
          1059,
          1372
        ],
        [
          1101,
          1379
        ],
        [
          1108,
          1347
        ],
        [
          1153,
          1356
        ],
        [
          1146,
          1386
        ],
        [
          1169,
          1390
        ],
        [
          1173,
          1387
        ],
        [
          1178,
          1358
        ],
        [
          1221,
          1365
        ],
        [
          1216,
          1397
        ],
        [
          1242,
          1401
        ],
        [
          1247,
          1399
        ],
        [
          1253,
          1369
        ],
        [
          1299,
          1378
        ],
        [
          1295,
          1411
        ],
        [
          1331,
          1416
        ],
        [
          1337,
          1385
        ],
        [
          1381,
          1391
        ],
        [
          1376,
          1426
        ],
        [
          1404,
          1428
        ],
        [
          1413,
          1394
        ],
        [
          1464,
          1404
        ],
        [
          1459,
          1437
        ],
        [
          1488,
          1444
        ],
        [
          1491,
          1442
        ],
        [
          1499,
          1409
        ],
        [
          1532,
          1414
        ],
        [
          1554,
          1423
        ],
        [
          1549,
          1456
        ],
        [
          1587,
          1460
        ],
        [
          1595,
          1425
        ],
        [
          1651,
          1436
        ],
        [
          1646,
          1473
        ],
        [
          1685,
          1476
        ],
        [
          1691,
          1443
        ],
        [
          1764,
          1454
        ],
        [
          1760,
          1492
        ],
        [
          1773,
          1492
        ],
        [
          1778,
          1456
        ],
        [
          1821,
          1464
        ],
        [
          1813,
          1535
        ],
        [
          1788,
          1540
        ],
        [
          1750,
          1540
        ],
        [
          1712,
          1547
        ],
        [
          1671,
          1548
        ],
        [
          1658,
          1552
        ]
      ]
    },
    {
      "line_color": null,
      "fill_color": null,
      "shape_type": "polygon",
      "label": "Wall",
      "group_id": 1,
      "points": [
        [
          1851,
          1541
        ],
        [
          1848,
          1529
        ],
        [
          1839,
          1523
        ],
        [
          1846,
          1467
        ],
        [
          1860,
          1470
        ],
        [
          1851,
          1541
        ]
      ]
    },
    {
      "line_color": null,
      "fill_color": null,
      "shape_type": "polygon",
      "label": "Wall",
      "group_id": 1,
      "points": [
        [
          2117,
          1494
        ],
        [
          1994,
          1478
        ],
        [
          1996,
          1473
        ],
        [
          2114,
          1487
        ],
        [
          2118,
          1489
        ],
        [
          2117,
          1494
        ]
      ]
    },
    {
      "line_color": null,
      "fill_color": null,
      "shape_type": "polygon",
      "label": "Wall",
      "group_id": 1,
      "points": [
        [
          2190,
          1513
        ],
        [
          2189,
          1504
        ],
        [
          2160,
          1501
        ],
        [
          2161,
          1493
        ],
        [
          2192,
          1495
        ],
        [
          2190,
          1513
        ]
      ]
    },
    {
      "line_color": null,
      "fill_color": null,
      "shape_type": "polygon",
      "label": "Wall",
      "group_id": 1,
      "points": [
        [
          2655,
          1616
        ],
        [
          2525,
          1590
        ],
        [
          2448,
          1570
        ],
        [
          2446,
          1567
        ],
        [
          2456,
          1530
        ],
        [
          2663,
          1572
        ],
        [
          2655,
          1616
        ]
      ]
    },
    {
      "line_color": null,
      "fill_color": null,
      "shape_type": "polygon",
      "label": "Wall",
      "group_id": 1,
      "points": [
        [
          2715,
          1623
        ],
        [
          2660,
          1616
        ],
        [
          2668,
          1573
        ],
        [
          2723,
          1582
        ],
        [
          2715,
          1623
        ]
      ]
    },
    {
      "line_color": null,
      "fill_color": null,
      "shape_type": "polygon",
      "label": "Wall",
      "group_id": 1,
      "points": [
        [
          4031,
          2195
        ],
        [
          3723,
          2071
        ],
        [
          3140,
          1807
        ],
        [
          2920,
          1714
        ],
        [
          2769,
          1654
        ],
        [
          2719,
          1630
        ],
        [
          2729,
          1585
        ],
        [
          2734,
          1583
        ],
        [
          2732,
          1593
        ],
        [
          2740,
          1595
        ],
        [
          2744,
          1585
        ],
        [
          2888,
          1614
        ],
        [
          2914,
          1612
        ],
        [
          2977,
          1653
        ],
        [
          3001,
          1662
        ],
        [
          3004,
          1654
        ],
        [
          3038,
          1660
        ],
        [
          3036,
          1675
        ],
        [
          3053,
          1682
        ],
        [
          3056,
          1681
        ],
        [
          3060,
          1665
        ],
        [
          3104,
          1672
        ],
        [
          3100,
          1699
        ],
        [
          3112,
          1704
        ],
        [
          3119,
          1678
        ],
        [
          3160,
          1685
        ],
        [
          3159,
          1702
        ],
        [
          3167,
          1704
        ],
        [
          3168,
          1709
        ],
        [
          3173,
          1688
        ],
        [
          3189,
          1688
        ],
        [
          3217,
          1695
        ],
        [
          3215,
          1712
        ],
        [
          3223,
          1715
        ],
        [
          3215,
          1717
        ],
        [
          3222,
          1721
        ],
        [
          3227,
          1719
        ],
        [
          3232,
          1698
        ],
        [
          3273,
          1706
        ],
        [
          3271,
          1729
        ],
        [
          3282,
          1728
        ],
        [
          3283,
          1726
        ],
        [
          3284,
          1715
        ],
        [
          3288,
          1711
        ],
        [
          3285,
          1689
        ],
        [
          3345,
          1701
        ],
        [
          3338,
          1715
        ],
        [
          3340,
          1721
        ],
        [
          3341,
          1718
        ],
        [
          3352,
          1718
        ],
        [
          3381,
          1727
        ],
        [
          3380,
          1737
        ],
        [
          3383,
          1738
        ],
        [
          3391,
          1740
        ],
        [
          3394,
          1727
        ],
        [
          3398,
          1725
        ],
        [
          3436,
          1731
        ],
        [
          3433,
          1759
        ],
        [
          3452,
          1757
        ],
        [
          3455,
          1736
        ],
        [
          3496,
          1742
        ],
        [
          3495,
          1764
        ],
        [
          3501,
          1768
        ],
        [
          3510,
          1769
        ],
        [
          3519,
          1743
        ],
        [
          3513,
          1736
        ],
        [
          3516,
          1735
        ],
        [
          3572,
          1747
        ],
        [
          3568,
          1768
        ],
        [
          3573,
          1770
        ],
        [
          3574,
          1778
        ],
        [
          3577,
          1759
        ],
        [
          3619,
          1765
        ],
        [
          3617,
          1778
        ],
        [
          3630,
          1781
        ],
        [
          3634,
          1786
        ],
        [
          3638,
          1768
        ],
        [
          3679,
          1774
        ],
        [
          3679,
          1796
        ],
        [
          3696,
          1797
        ],
        [
          3701,
          1781
        ],
        [
          3706,
          1779
        ],
        [
          3744,
          1790
        ],
        [
          3740,
          1809
        ],
        [
          3751,
          1808
        ],
        [
          3757,
          1802
        ],
        [
          3758,
          1791
        ],
        [
          3754,
          1779
        ],
        [
          4031,
          1834
        ],
        [
          4031,
          1897
        ],
        [
          4026,
          1897
        ],
        [
          3908,
          1877
        ],
        [
          3662,
          1842
        ],
        [
          3556,
          1831
        ],
        [
          3546,
          1823
        ],
        [
          3548,
          1814
        ],
        [
          3545,
          1810
        ],
        [
          3525,
          1811
        ],
        [
          3501,
          1797
        ],
        [
          3469,
          1789
        ],
        [
          3458,
          1791
        ],
        [
          3453,
          1798
        ],
        [
          3465,
          1817
        ],
        [
          3431,
          1817
        ],
        [
          3400,
          1798
        ],
        [
          3386,
          1799
        ],
        [
          3368,
          1792
        ],
        [
          3365,
          1797
        ],
        [
          3831,
          1973
        ],
        [
          4031,
          2041
        ],
        [
          4031,
          2195
        ]
      ]
    },
    {
      "line_color": null,
      "fill_color": null,
      "shape_type": "polygon",
      "label": "Wall",
      "group_id": 1,
      "points": [
        [
          2169,
          1911
        ],
        [
          2124,
          1875
        ],
        [
          2140,
          1814
        ],
        [
          2139,
          1756
        ],
        [
          2184,
          1797
        ],
        [
          2187,
          1805
        ],
        [
          2190,
          1841
        ],
        [
          2179,
          1886
        ],
        [
          2169,
          1911
        ]
      ]
    },
    {
      "line_color": null,
      "fill_color": null,
      "shape_type": "polygon",
      "label": "Wall",
      "group_id": 1,
      "points": [
        [
          3305,
          1775
        ],
        [
          3299,
          1763
        ],
        [
          3295,
          1763
        ],
        [
          3289,
          1769
        ],
        [
          3305,
          1775
        ]
      ]
    },
    {
      "line_color": null,
      "fill_color": null,
      "shape_type": "polygon",
      "label": "Wall",
      "group_id": 1,
      "points": [
        [
          3334,
          1786
        ],
        [
          3334,
          1778
        ],
        [
          3326,
          1776
        ],
        [
          3320,
          1781
        ],
        [
          3334,
          1786
        ]
      ]
    },
    {
      "line_color": null,
      "fill_color": null,
      "shape_type": "polygon",
      "label": "Barrier",
      "group_id": 2,
      "points": [
        [
          2111,
          1515
        ],
        [
          2014,
          1499
        ],
        [
          1989,
          1479
        ],
        [
          2117,
          1494
        ],
        [
          2111,
          1515
        ]
      ]
    },
    {
      "line_color": null,
      "fill_color": null,
      "shape_type": "polygon",
      "label": "Barrier",
      "group_id": 2,
      "points": [
        [
          2188,
          1529
        ],
        [
          2155,
          1522
        ],
        [
          2159,
          1502
        ],
        [
          2189,
          1504
        ],
        [
          2188,
          1529
        ]
      ]
    }
  ]
}